topsis/__init__.py
topsis/topsis.py
Topsis_Nandini_102067009-1.1.4.dist-info/LICENSE
Topsis_Nandini_102067009-1.1.4.dist-info/METADATA
Topsis_Nandini_102067009-1.1.4.dist-info/WHEEL
Topsis_Nandini_102067009-1.1.4.dist-info/entry_points.txt
Topsis_Nandini_102067009-1.1.4.dist-info/top_level.txt
Topsis_Nandini_102067009-1.1.4.dist-info/RECORD
