Metadata-Version: 2.1
Name: Topsis-Nandini-102067009
Version: 1.1.4
Summary: API and CLI tool to calculate Topsis, CLI tool inputs CSV/Excel files
Home-page: https://github.com/NandiniMehta0603/Topsis
Author: Nandini Mehta
Author-email: mehtanandini684@gmail.com
License: MIT
Keywords: topsis,python,pypi,csv,xlsx,xls,cli
Platform: UNKNOWN
License-File: LICENSE
Requires-Dist: numpy
Requires-Dist: pandas
